diagram_autobuild/__init__.py
diagram_autobuild/tool.py
diagram_autobuild/util.py
diagram_autobuild/view.py
diagram_autobuild/cmd/__init__.py
diagram_autobuild/cmd/diagram_autobuild_cmd.py
diagram_autobuild/templates/index.html
diagram_autobuild/test/__init__.py
diagram_autobuild/test/test_tool.py
diagram_autobuild/test/test_util.py
diagram_autobuild/test/test_view.py
diagram_autobuild-0.1.0.dist-info/DESCRIPTION.rst
diagram_autobuild-0.1.0.dist-info/METADATA
diagram_autobuild-0.1.0.dist-info/RECORD
diagram_autobuild-0.1.0.dist-info/WHEEL
diagram_autobuild-0.1.0.dist-info/entry_points.txt
diagram_autobuild-0.1.0.dist-info/metadata.json
diagram_autobuild-0.1.0.dist-info/top_level.txt
