Metadata-Version: 2.0
Name: diagram-autobuild
Version: 0.1.0
Summary: diagram-autobuild improves the efficiency of the making diagrams
Home-page: https://github.com/momijiame/diagram-autobuild
Author: momijiame
Author-email: amedama.ginmokusei@gmail.com
License: Apache License, Version 2.0
Platform: UNKNOWN
Classifier: Development Status :: 4 - Beta
Classifier: Programming Language :: Python
Classifier: Intended Audience :: Developers
Classifier: Operating System :: POSIX
Classifier: Programming Language :: Python :: 2
Classifier: Programming Language :: Python :: 2.7
Classifier: Programming Language :: Python :: 3
Classifier: Programming Language :: Python :: 3.3
Classifier: Programming Language :: Python :: 3.4
Classifier: Programming Language :: Python :: 3.5
Classifier: Programming Language :: Python :: 3.6
Requires-Dist: click
Requires-Dist: future
Requires-Dist: Jinja2
Requires-Dist: livereload
Provides-Extra: testing
Requires-Dist: pytest; extra == 'testing'
Requires-Dist: pytest-pep8; extra == 'testing'
